[{"province":"Banten","city":"Tangerang","district":"Legok","urban":"Rancagong","postal_code":15820},{"province":"Banten","city":"Tangerang","district":"Legok","urban":"Serdang Wetan","postal_code":15820},{"province":"Banten","city":"Tangerang","district":"Legok","urban":"Legok","postal_code":15820},{"province":"Banten","city":"Tangerang","district":"Legok","urban":"Pala Sari","postal_code":15820},{"province":"Banten","city":"Tangerang","district":"Legok","urban":"Cirarab","postal_code":15820},{"province":"Banten","city":"Tangerang","district":"Legok","urban":"Kamuning (Kemuning)","postal_code":15820},{"province":"Banten","city":"Tangerang","district":"Legok","urban":"Caringin","postal_code":15820},{"province":"Banten","city":"Tangerang","district":"Legok","urban":"Ciangir","postal_code":15820},{"province":"Banten","city":"Tangerang","district":"Legok","urban":"Babat","postal_code":15820},{"province":"Banten","city":"Tangerang","district":"Legok","urban":"Bojong Kamal","postal_code":15820},{"province":"Banten","city":"Tangerang","district":"Legok","urban":"Babakan","postal_code":15820}]