[{"province":"Nanggroe Aceh Darussalam","city":"Aceh Besar","district":"Kota Jantho","urban":"Suka Tani","postal_code":23917},{"province":"Nanggroe Aceh Darussalam","city":"Aceh Besar","district":"Kota Jantho","urban":"Weu","postal_code":23917},{"province":"Nanggroe Aceh Darussalam","city":"Aceh Besar","district":"Kota Jantho","urban":"Jantho Baru","postal_code":23917},{"province":"Nanggroe Aceh Darussalam","city":"Aceh Besar","district":"Kota Jantho","urban":"Jantho Makmur","postal_code":23917},{"province":"Nanggroe Aceh Darussalam","city":"Aceh Besar","district":"Kota Jantho","urban":"Beung","postal_code":23917},{"province":"Nanggroe Aceh Darussalam","city":"Aceh Besar","district":"Kota Jantho","urban":"Data Cut","postal_code":23917},{"province":"Nanggroe Aceh Darussalam","city":"Aceh Besar","district":"Kota Jantho","urban":"Awee","postal_code":23917}]