[{"province":"Sumatera Selatan","city":"Ogan Komering Ulu Timur","district":"Martapura","urban":"Veteran Jaya","postal_code":32315},{"province":"Sumatera Selatan","city":"Ogan Komering Ulu Timur","district":"Martapura","urban":"Tanjung Kemala","postal_code":32315},{"province":"Sumatera Selatan","city":"Ogan Komering Ulu Timur","district":"Martapura","urban":"Tanjung Kemala Barat","postal_code":32315},{"province":"Sumatera Selatan","city":"Ogan Komering Ulu Timur","district":"Martapura","urban":"Terukis Rahayu","postal_code":32315},{"province":"Sumatera Selatan","city":"Ogan Komering Ulu Timur","district":"Martapura","urban":"Sungai Tuha Jaya","postal_code":32315},{"province":"Sumatera Selatan","city":"Ogan Komering Ulu Timur","district":"Martapura","urban":"Kota Baru Selatan","postal_code":32315},{"province":"Sumatera Selatan","city":"Ogan Komering Ulu Timur","district":"Martapura","urban":"Bukit Sari","postal_code":32315},{"province":"Sumatera Selatan","city":"Ogan Komering Ulu Timur","district":"Martapura","urban":"Kota Baru Barat","postal_code":32315}]