[{"province":"Jawa Barat","city":"Karawang","district":"Batujaya","urban":"Telukambulu","postal_code":41354},{"province":"Jawa Barat","city":"Karawang","district":"Batujaya","urban":"Telukbango","postal_code":41354},{"province":"Jawa Barat","city":"Karawang","district":"Batujaya","urban":"Segaran","postal_code":41354},{"province":"Jawa Barat","city":"Karawang","district":"Batujaya","urban":"Segarjaya","postal_code":41354},{"province":"Jawa Barat","city":"Karawang","district":"Batujaya","urban":"Kutaampel","postal_code":41354},{"province":"Jawa Barat","city":"Karawang","district":"Batujaya","urban":"Karyamakmur","postal_code":41354},{"province":"Jawa Barat","city":"Karawang","district":"Batujaya","urban":"Karyamulya","postal_code":41354},{"province":"Jawa Barat","city":"Karawang","district":"Batujaya","urban":"Karyabakti","postal_code":41354},{"province":"Jawa Barat","city":"Karawang","district":"Batujaya","urban":"Batujaya","postal_code":41354},{"province":"Jawa Barat","city":"Karawang","district":"Batujaya","urban":"Baturaden","postal_code":41354}]