[{"province":"Jawa Tengah","city":"Magelang","district":"Windusari","urban":"Wonoroto","postal_code":56152},{"province":"Jawa Tengah","city":"Magelang","district":"Windusari","urban":"Umbulsari","postal_code":56152},{"province":"Jawa Tengah","city":"Magelang","district":"Windusari","urban":"Windusari","postal_code":56152},{"province":"Jawa Tengah","city":"Magelang","district":"Windusari","urban":"Semen","postal_code":56152},{"province":"Jawa Tengah","city":"Magelang","district":"Windusari","urban":"Tanjungsari","postal_code":56152},{"province":"Jawa Tengah","city":"Magelang","district":"Windusari","urban":"Ngemplak","postal_code":56152},{"province":"Jawa Tengah","city":"Magelang","district":"Windusari","urban":"Pasangsari","postal_code":56152},{"province":"Jawa Tengah","city":"Magelang","district":"Windusari","urban":"Kentengsari","postal_code":56152},{"province":"Jawa Tengah","city":"Magelang","district":"Windusari","urban":"Mangunsari","postal_code":56152},{"province":"Jawa Tengah","city":"Magelang","district":"Windusari","urban":"Gunungsari","postal_code":56152},{"province":"Jawa Tengah","city":"Magelang","district":"Windusari","urban":"Kalijoso","postal_code":56152},{"province":"Jawa Tengah","city":"Magelang","district":"Windusari","urban":"Kembangkuning","postal_code":56152},{"province":"Jawa Tengah","city":"Magelang","district":"Windusari","urban":"Girimulyo","postal_code":56152},{"province":"Jawa Tengah","city":"Magelang","district":"Windusari","urban":"Gondangrejo","postal_code":56152},{"province":"Jawa Tengah","city":"Magelang","district":"Windusari","urban":"Candisari","postal_code":56152},{"province":"Jawa Tengah","city":"Magelang","district":"Windusari","urban":"Dampit","postal_code":56152},{"province":"Jawa Tengah","city":"Magelang","district":"Windusari","urban":"Genito","postal_code":56152},{"province":"Jawa Tengah","city":"Magelang","district":"Windusari","urban":"Bandarsedayu","postal_code":56152},{"province":"Jawa Tengah","city":"Magelang","district":"Windusari","urban":"Banjarsari","postal_code":56152},{"province":"Jawa Tengah","city":"Magelang","district":"Windusari","urban":"Balesari","postal_code":56152}]