[{"province":"Jawa Tengah","city":"Boyolali","district":"Klego","urban":"Sumber Agung","postal_code":57385},{"province":"Jawa Tengah","city":"Boyolali","district":"Klego","urban":"Tanjung","postal_code":57385},{"province":"Jawa Tengah","city":"Boyolali","district":"Klego","urban":"Sangge","postal_code":57385},{"province":"Jawa Tengah","city":"Boyolali","district":"Klego","urban":"Sendangrejo","postal_code":57385},{"province":"Jawa Tengah","city":"Boyolali","district":"Klego","urban":"Klego","postal_code":57385},{"province":"Jawa Tengah","city":"Boyolali","district":"Klego","urban":"Karanggatak","postal_code":57385},{"province":"Jawa Tengah","city":"Boyolali","district":"Klego","urban":"Karangmojo","postal_code":57385},{"province":"Jawa Tengah","city":"Boyolali","district":"Klego","urban":"Kalangan","postal_code":57385},{"province":"Jawa Tengah","city":"Boyolali","district":"Klego","urban":"Jaten","postal_code":57385},{"province":"Jawa Tengah","city":"Boyolali","district":"Klego","urban":"Gondanglegi","postal_code":57385},{"province":"Jawa Tengah","city":"Boyolali","district":"Klego","urban":"Blumbang","postal_code":57385},{"province":"Jawa Tengah","city":"Boyolali","district":"Klego","urban":"Bade","postal_code":57385},{"province":"Jawa Tengah","city":"Boyolali","district":"Klego","urban":"Banyu Urip","postal_code":57385}]