[{"province":"Jawa Tengah","city":"Wonogiri","district":"Batuwarno","urban":"Tegiri","postal_code":57674},{"province":"Jawa Tengah","city":"Wonogiri","district":"Batuwarno","urban":"Sumberagung","postal_code":57674},{"province":"Jawa Tengah","city":"Wonogiri","district":"Batuwarno","urban":"Sumberejo","postal_code":57674},{"province":"Jawa Tengah","city":"Wonogiri","district":"Batuwarno","urban":"Ronggojati","postal_code":57674},{"province":"Jawa Tengah","city":"Wonogiri","district":"Batuwarno","urban":"Selopuro","postal_code":57674},{"province":"Jawa Tengah","city":"Wonogiri","district":"Batuwarno","urban":"Sendangsari","postal_code":57674},{"province":"Jawa Tengah","city":"Wonogiri","district":"Batuwarno","urban":"Batuwarno","postal_code":57674},{"province":"Jawa Tengah","city":"Wonogiri","district":"Batuwarno","urban":"Kudi","postal_code":57674}]