[{"province":"Jawa Tengah","city":"Pati","district":"Gunungwungkal","urban":"Sidomulyo","postal_code":59156},{"province":"Jawa Tengah","city":"Pati","district":"Gunungwungkal","urban":"Sumberejo","postal_code":59156},{"province":"Jawa Tengah","city":"Pati","district":"Gunungwungkal","urban":"Pesagen","postal_code":59156},{"province":"Jawa Tengah","city":"Pati","district":"Gunungwungkal","urban":"Sampok","postal_code":59156},{"province":"Jawa Tengah","city":"Pati","district":"Gunungwungkal","urban":"Jrahi","postal_code":59156},{"province":"Jawa Tengah","city":"Pati","district":"Gunungwungkal","urban":"Ngetuk","postal_code":59156},{"province":"Jawa Tengah","city":"Pati","district":"Gunungwungkal","urban":"Perdopo","postal_code":59156},{"province":"Jawa Tengah","city":"Pati","district":"Gunungwungkal","urban":"Jembulwunut","postal_code":59156},{"province":"Jawa Tengah","city":"Pati","district":"Gunungwungkal","urban":"Jepalo","postal_code":59156},{"province":"Jawa Tengah","city":"Pati","district":"Gunungwungkal","urban":"Gunungwungkal","postal_code":59156},{"province":"Jawa Tengah","city":"Pati","district":"Gunungwungkal","urban":"Gulangpungge","postal_code":59156},{"province":"Jawa Tengah","city":"Pati","district":"Gunungwungkal","urban":"Gajihan","postal_code":59156},{"province":"Jawa Tengah","city":"Pati","district":"Gunungwungkal","urban":"Giling","postal_code":59156},{"province":"Jawa Tengah","city":"Pati","district":"Gunungwungkal","urban":"Bancak","postal_code":59156},{"province":"Jawa Tengah","city":"Pati","district":"Gunungwungkal","urban":"Gadu","postal_code":59156}]