[{"province":"Jawa Timur","city":"Pacitan","district":"Arjosari","urban":"Tremas","postal_code":63581},{"province":"Jawa Timur","city":"Pacitan","district":"Arjosari","urban":"Temon","postal_code":63581},{"province":"Jawa Timur","city":"Pacitan","district":"Arjosari","urban":"Sedayu","postal_code":63581},{"province":"Jawa Timur","city":"Pacitan","district":"Arjosari","urban":"Pagutan","postal_code":63581},{"province":"Jawa Timur","city":"Pacitan","district":"Arjosari","urban":"Mangunharjo","postal_code":63581},{"province":"Jawa Timur","city":"Pacitan","district":"Arjosari","urban":"Mlati","postal_code":63581},{"province":"Jawa Timur","city":"Pacitan","district":"Arjosari","urban":"Kedungbendo","postal_code":63581},{"province":"Jawa Timur","city":"Pacitan","district":"Arjosari","urban":"Karangrejo","postal_code":63581},{"province":"Jawa Timur","city":"Pacitan","district":"Arjosari","urban":"Karanggede","postal_code":63581},{"province":"Jawa Timur","city":"Pacitan","district":"Arjosari","urban":"Jetis Kidul","postal_code":63581},{"province":"Jawa Timur","city":"Pacitan","district":"Arjosari","urban":"Jatimalang","postal_code":63581},{"province":"Jawa Timur","city":"Pacitan","district":"Arjosari","urban":"Gembong","postal_code":63581},{"province":"Jawa Timur","city":"Pacitan","district":"Arjosari","urban":"Gunungsari","postal_code":63581},{"province":"Jawa Timur","city":"Pacitan","district":"Arjosari","urban":"Gayuhan","postal_code":63581},{"province":"Jawa Timur","city":"Pacitan","district":"Arjosari","urban":"Gegeran","postal_code":63581},{"province":"Jawa Timur","city":"Pacitan","district":"Arjosari","urban":"Arjosari","postal_code":63581},{"province":"Jawa Timur","city":"Pacitan","district":"Arjosari","urban":"Borang","postal_code":63581}]