[{"province":"Sulawesi Selatan","city":"Wajo","district":"Keera","urban":"Paojepe","postal_code":90993},{"province":"Sulawesi Selatan","city":"Wajo","district":"Keera","urban":"Pattirolokka","postal_code":90993},{"province":"Sulawesi Selatan","city":"Wajo","district":"Keera","urban":"Labawang","postal_code":90993},{"province":"Sulawesi Selatan","city":"Wajo","district":"Keera","urban":"Lalliseng","postal_code":90993},{"province":"Sulawesi Selatan","city":"Wajo","district":"Keera","urban":"Ciromanie","postal_code":90993},{"province":"Sulawesi Selatan","city":"Wajo","district":"Keera","urban":"Inrello","postal_code":90993},{"province":"Sulawesi Selatan","city":"Wajo","district":"Keera","urban":"Keera","postal_code":90993},{"province":"Sulawesi Selatan","city":"Wajo","district":"Keera","urban":"Awota","postal_code":90993},{"province":"Sulawesi Selatan","city":"Wajo","district":"Keera","urban":"Ballaere (Ballere)","postal_code":90993},{"province":"Sulawesi Selatan","city":"Wajo","district":"Keera","urban":"Awo","postal_code":90993}]