[{"province":"Sulawesi Selatan","city":"Toraja Utara","district":"Tallunglipu","urban":"Tantanan Tallunglipu","postal_code":91832},{"province":"Sulawesi Selatan","city":"Toraja Utara","district":"Tallunglipu","urban":"Tallunglipu Matallo","postal_code":91832},{"province":"Sulawesi Selatan","city":"Toraja Utara","district":"Tallunglipu","urban":"Tampo Tallunglipu","postal_code":91832},{"province":"Sulawesi Selatan","city":"Toraja Utara","district":"Tallunglipu","urban":"Rantepaku Tallunglipu","postal_code":91832},{"province":"Sulawesi Selatan","city":"Toraja Utara","district":"Tallunglipu","urban":"Tagari Tallunglipu","postal_code":91832},{"province":"Sulawesi Selatan","city":"Toraja Utara","district":"Tallunglipu","urban":"Tallunglipu","postal_code":91832},{"province":"Sulawesi Selatan","city":"Toraja Utara","district":"Tallunglipu","urban":"Buntu Tallunglipu","postal_code":91832}]