[{"province":"Sulawesi Selatan","city":"Bulukumba","district":"Kindang","urban":"Sopa","postal_code":92517},{"province":"Sulawesi Selatan","city":"Bulukumba","district":"Kindang","urban":"Tamaona","postal_code":92517},{"province":"Sulawesi Selatan","city":"Bulukumba","district":"Kindang","urban":"Sipaenre","postal_code":92517},{"province":"Sulawesi Selatan","city":"Bulukumba","district":"Kindang","urban":"Somba Palioli","postal_code":92517},{"province":"Sulawesi Selatan","city":"Bulukumba","district":"Kindang","urban":"Mattirowalie","postal_code":92517},{"province":"Sulawesi Selatan","city":"Bulukumba","district":"Kindang","urban":"Oro Gading","postal_code":92517},{"province":"Sulawesi Selatan","city":"Bulukumba","district":"Kindang","urban":"Kindang","postal_code":92517},{"province":"Sulawesi Selatan","city":"Bulukumba","district":"Kindang","urban":"Kahayya","postal_code":92517},{"province":"Sulawesi Selatan","city":"Bulukumba","district":"Ujung Bulu","urban":"Caile","postal_code":92517},{"province":"Sulawesi Selatan","city":"Bulukumba","district":"Kindang","urban":"Garuntungan","postal_code":92517},{"province":"Sulawesi Selatan","city":"Bulukumba","district":"Kindang","urban":"Benteng Palioi","postal_code":92517},{"province":"Sulawesi Selatan","city":"Bulukumba","district":"Kindang","urban":"Borong Rappoa","postal_code":92517},{"province":"Sulawesi Selatan","city":"Bulukumba","district":"Kindang","urban":"Anrihua","postal_code":92517},{"province":"Sulawesi Selatan","city":"Bulukumba","district":"Kindang","urban":"Balibo","postal_code":92517}]